{
    "swagger": "2.0",
    "info": {
        "title": "functiondev-swagger.azurewebsites.net",
        "version": "1.0.0"
    },
    "host": "functiondev-swagger.azurewebsites.net",
    "basePath": "/",
    "schemes": [
        "https",
        "http"
    ],
    "paths": {
        "/api/HttpTriggerJS1": {
            "post": {
                "operationId": "/api/HttpTriggerJS1/post",
                "produces": [],
                "consumes": [],
                "parameters": [],
                "description": "Replace with Operation Object #http://swagger.io/specification/#operationObject",
                "responses": {
                    "200": {
                        "description": "Success operation"
                    }
                },
                "security": [
                    {
                        "apikeyQuery": []
                    }
                ]
            }
        },
        "/api/HttpTriggerJS2": {
            "get": {
                "operationId": "/api/HttpTriggerJS2/get",
                "produces": [],
                "consumes": [],
                "parameters": [],
                "description": "Replace with Operation Object #http://swagger.io/specification/#operationObject",
                "responses": {
                    "200": {
                        "description": "Success operation"
                    }
                },
                "security": [
                    {
                        "apikeyQuery": []
                    }
                ]
            },
            "post": {
                "operationId": "/api/HttpTriggerJS2/post",
                "produces": [],
                "consumes": [],
                "parameters": [],
                "description": "Replace with Operation Object #http://swagger.io/specification/#operationObject",
                "responses": {
                    "200": {
                        "description": "Success operation"
                    }
                },
                "security": [
                    {
                        "apikeyQuery": []
                    }
                ]
            },
            "delete": {
                "operationId": "/api/HttpTriggerJS2/delete",
                "produces": [],
                "consumes": [],
                "parameters": [],
                "description": "Replace with Operation Object #http://swagger.io/specification/#operationObject",
                "responses": {
                    "200": {
                        "description": "Success operation"
                    }
                },
                "security": [
                    {
                        "apikeyQuery": []
                    }
                ]
            },
            "head": {
                "operationId": "/api/HttpTriggerJS2/head",
                "produces": [],
                "consumes": [],
                "parameters": [],
                "description": "Replace with Operation Object #http://swagger.io/specification/#operationObject",
                "responses": {
                    "200": {
                        "description": "Success operation"
                    }
                },
                "security": [
                    {
                        "apikeyQuery": []
                    }
                ]
            },
            "patch": {
                "operationId": "/api/HttpTriggerJS2/patch",
                "produces": [],
                "consumes": [],
                "parameters": [],
                "description": "Replace with Operation Object #http://swagger.io/specification/#operationObject",
                "responses": {
                    "200": {
                        "description": "Success operation"
                    }
                },
                "security": [
                    {
                        "apikeyQuery": []
                    }
                ]
            },
            "put": {
                "operationId": "/api/HttpTriggerJS2/put",
                "produces": [],
                "consumes": [],
                "parameters": [],
                "description": "Replace with Operation Object #http://swagger.io/specification/#operationObject",
                "responses": {
                    "200": {
                        "description": "Success operation"
                    }
                },
                "security": [
                    {
                        "apikeyQuery": []
                    }
                ]
            },
            "options": {
                "operationId": "/api/HttpTriggerJS2/options",
                "produces": [],
                "consumes": [],
                "parameters": [],
                "description": "Replace with Operation Object #http://swagger.io/specification/#operationObject",
                "responses": {
                    "200": {
                        "description": "Success operation"
                    }
                },
                "security": [
                    {
                        "apikeyQuery": []
                    }
                ]
            }
        }
    },
    "definitions": {},
    "securityDefinitions": {
        "apikeyQuery": {
            "type": "apiKey",
            "name": "code",
            "in": "query"
        }
    }
}